ollama_instructor/__init__.py
ollama_instructor/_logging.py
ollama_instructor/ollama_instructor.py
ollama_instructor/py.typed
ollama_instructor-1.1.0.dist-info/METADATA
ollama_instructor-1.1.0.dist-info/WHEEL
ollama_instructor-1.1.0.dist-info/licenses/LICENSE
ollama_instructor-1.1.0.dist-info/RECORD
