Metadata-Version: 2.4
Name: ollama-instructor
Version: 1.1.0
Summary: Validate structured outputs from LLMs with Ollama and automatic retries.
Author-email: Lennart Pollvogt <lennartpollvogt@protonmail.com>
License-File: LICENSE
Keywords: instructor,json,json-schema,llm,local-llm,ollama,prompting,pydantic,validation
Classifier: Operating System :: OS Independent
Classifier: Programming Language :: Python :: 3
Classifier: Topic :: Scientific/Engineering :: Artificial Intelligence
Requires-Python: >=3.10
Requires-Dist: ollama>=0.4.4
Requires-Dist: pydantic>=2.10.4
Requires-Dist: stamina>=24.3.0
